LICENSE
MANIFEST.in
README.md
setup.py
pracnbastats/__init__.py
pracnbastats/allplayers.py
pracnbastats/currentteams.py
pracnbastats/exceptions.py
pracnbastats/league.py
pracnbastats/params.py
pracnbastats/player.py
pracnbastats/playtype.py
pracnbastats/scrape.py
pracnbastats/store.py
pracnbastats/table.py
pracnbastats/team.py
pracnbastats/teamhistory.py
pracnbastats/utils.py
pracnbastats.egg-info/PKG-INFO
pracnbastats.egg-info/SOURCES.txt
pracnbastats.egg-info/dependency_links.txt
pracnbastats.egg-info/requires.txt
pracnbastats.egg-info/top_level.txt